<?xml version="1.0" encoding="ISO-8859-1"?>
<?xml-stylesheet type="text/xsl" href="helma.xsl"?>
<xmlroot xmlns:hop="http://www.helma.org/docs/guide/features/database">
  <hopobject id="4205" name="Word Work File D_1_files" prototype="Page" created="1467922510092" lastModified="1483599189803">
  <hop:parent idref="4200" prototyperef="Page"/>
    <http_browser>Mozilla/5.0 (Macintosh; Intel Mac OS X 10_8_5) AppleWebKit/537.36 (KHTML, like Gecko) Chrome/49.0.2623.112 Safari/537.36</http_browser>
    <lang>en-us</lang>
    <uri>Word Work File D_1_files</uri>
    <http_host>127.0.0.1:8080</http_host>
    <time type="date">07.07.2016 20:15:10 UTC</time>
    <pseudoparent idref="4200" prototyperef="Page"/>
    <http_remotehost>127.0.0.1</http_remotehost>
    <hopsession>127.0.0.gpqyzqzttlbb</hopsession>
    <user>jkridner.wordpress.com</user>
    <pvcount type="float">7.0</pvcount>
    <body>Dummy page</body>
    <http_language>en-US,en;q=0.8</http_language>
    <http_referer>http://beagleboard.org/blog-drafts/bbgw/Word%20Work%20File%20D_1_files/edit</http_referer>
  </hopobject>
</xmlroot>
