<?xml version="1.0" encoding="ISO-8859-1"?>
<?xml-stylesheet type="text/xsl" href="helma.xsl"?>
<xmlroot xmlns:hop="http://www.helma.org/docs/guide/features/database">
  <hopobject id="4254" name="asee" prototype="Page" created="1498595274011" lastModified="1498596650757">
  <hop:parent idref="3757" prototyperef="Page"/>
    <http_remotehost>127.0.0.1</http_remotehost>
    <http_language>en-US,en;q=0.8</http_language>
    <uri>asee</uri>
    <http_browser>Mozilla/5.0 (Macintosh; Intel Mac OS X 10_12_5) AppleWebKit/537.36 (KHTML, like Gecko) Chrome/59.0.3071.86 Safari/537.36</http_browser>
    <time type="date">27.06.2017 20:50:50 UTC</time>
    <hopsession>127.0.0.1doyt4mssbu6w</hopsession>
    <body>&lt;h1&gt;ASEE 2017&lt;/h1&gt;
&lt;div style=&quot;float:right;&quot;&gt;&lt;iframe width=&quot;560&quot; height=&quot;315&quot; src=&quot;https://www.youtube.com/embed/videoseries?list=PLzq-XagGEZrd4LjHrmvWApUv73-LrQtxF&quot; frameborder=&quot;0&quot; allowfullscreen&gt;&lt;/iframe&gt;&lt;/div&gt;
&lt;ul style=&quot;font-size:1.5em;&quot;&gt;
    &lt;li&gt;Contact e-mail: &lt;span id=&quot;email2&quot;&gt;&lt;/span&gt;&lt;/li&gt;
    &lt;li&gt;Slides: &lt;a href=&quot;https://drive.google.com/file/d/0B5UNMAgIJB74ZEowLVJ0ZFU0Mlk/view?usp=sharing&quot; class=&quot;external&quot;&gt;LEDs to Robots.pptx&lt;/a&gt;&lt;/li&gt;
    &lt;li&gt;&lt;a href=&quot;/blue&quot;&gt;BeagleBone Blue product info and purchase page&lt;/a&gt;&lt;/li&gt;
    &lt;li&gt;&lt;a href=&quot;http://renaissancerobotics.com/edumip.html&quot; class=&quot;external&quot;&gt;eduMIP product info and purchase page&lt;/a&gt;&lt;/li&gt;
    &lt;li&gt;&lt;a href=&quot;/getting-started&quot;&gt;Getting Started page (connecting to the board/IDE)&lt;/a&gt;&lt;/li&gt;
&lt;/ul&gt;
&lt;div style=&quot;clear:both;&quot;&gt;&lt;/div&gt;
&lt;h1&gt;&lt;a href=&quot;/show/asee2016&quot;&gt;ASEE 2016&lt;/a&gt;&lt;/h1&gt;
&lt;script&gt;
    var email1 = &quot;jkrXXXidner@beaXXXgleboard.oXXXrg&quot;.replace(/XXX/g,&apos;&apos;);
    var email2 = &quot;unXXXiv@XXXtXXXiXXX.comXXX&quot;.replace(/XXX/g,&apos;&apos;);
    $(&apos;#email1&apos;).html(&apos;&lt;a href=&quot;mailto:&apos; + email1 + &apos;&quot;&gt;&apos; + email1 +&apos;&lt;/a&gt;&apos;);
    $(&apos;#email2&apos;).html(&apos;&lt;a href=&quot;mailto:&apos; + email2 + &apos;&quot;&gt;&apos; + email2 +&apos;&lt;/a&gt;&apos;);
&lt;/script&gt;</body>
    <pseudoparent idref="3757" prototyperef="Page"/>
    <pvcount type="float">16.0</pvcount>
    <http_referer>https://beagleboard.org/show/asee/edit</http_referer>
    <http_host>127.0.0.1:8080</http_host>
    <user>jkridner.wordpress.com</user>
    <lang>en-us</lang>
  </hopobject>
</xmlroot>
